onnx2tf/__init__.py
onnx2tf/__main__.py
onnx2tf/onnx2tf.py
onnx2tf/ops/Abs.py
onnx2tf/ops/Acos.py
onnx2tf/ops/Acosh.py
onnx2tf/ops/Add.py
onnx2tf/ops/AffineGrid.py
onnx2tf/ops/And.py
onnx2tf/ops/ArgMax.py
onnx2tf/ops/ArgMin.py
onnx2tf/ops/Asin.py
onnx2tf/ops/Asinh.py
onnx2tf/ops/Atan.py
onnx2tf/ops/Atanh.py
onnx2tf/ops/Attention.py
onnx2tf/ops/AveragePool.py
onnx2tf/ops/BatchNormalization.py
onnx2tf/ops/Bernoulli.py
onnx2tf/ops/BitShift.py
onnx2tf/ops/BitwiseAnd.py
onnx2tf/ops/BitwiseNot.py
onnx2tf/ops/BitwiseOr.py
onnx2tf/ops/BitwiseXor.py
onnx2tf/ops/BlackmanWindow.py
onnx2tf/ops/Cast.py
onnx2tf/ops/Ceil.py
onnx2tf/ops/Celu.py
onnx2tf/ops/Clip.py
onnx2tf/ops/Col2Im.py
onnx2tf/ops/Compress.py
onnx2tf/ops/Concat.py
onnx2tf/ops/ConcatFromSequence.py
onnx2tf/ops/Constant.py
onnx2tf/ops/ConstantOfShape.py
onnx2tf/ops/Conv.py
onnx2tf/ops/ConvInteger.py
onnx2tf/ops/ConvTranspose.py
onnx2tf/ops/Cos.py
onnx2tf/ops/Cosh.py
onnx2tf/ops/CumProd.py
onnx2tf/ops/CumSum.py
onnx2tf/ops/DFT.py
onnx2tf/ops/DeformConv.py
onnx2tf/ops/DepthToSpace.py
onnx2tf/ops/DequantizeLinear.py
onnx2tf/ops/Det.py
onnx2tf/ops/Div.py
onnx2tf/ops/Dropout.py
onnx2tf/ops/DynamicQuantizeLinear.py
onnx2tf/ops/Einsum.py
onnx2tf/ops/Elu.py
onnx2tf/ops/Equal.py
onnx2tf/ops/Erf.py
onnx2tf/ops/Exp.py
onnx2tf/ops/Expand.py
onnx2tf/ops/EyeLike.py
onnx2tf/ops/Flatten.py
onnx2tf/ops/Floor.py
onnx2tf/ops/FusedConv.py
onnx2tf/ops/GRU.py
onnx2tf/ops/Gather.py
onnx2tf/ops/GatherElements.py
onnx2tf/ops/GatherND.py
onnx2tf/ops/Gelu.py
onnx2tf/ops/Gemm.py
onnx2tf/ops/GlobalAveragePool.py
onnx2tf/ops/GlobalLpPool.py
onnx2tf/ops/GlobalMaxPool.py
onnx2tf/ops/Greater.py
onnx2tf/ops/GreaterOrEqual.py
onnx2tf/ops/GridSample.py
onnx2tf/ops/GroupNorm.py
onnx2tf/ops/HammingWindow.py
onnx2tf/ops/HannWindow.py
onnx2tf/ops/HardSigmoid.py
onnx2tf/ops/HardSwish.py
onnx2tf/ops/Hardmax.py
onnx2tf/ops/Identity.py
onnx2tf/ops/If.py
onnx2tf/ops/ImageDecoder.py
onnx2tf/ops/Input.py
onnx2tf/ops/InstanceNormalization.py
onnx2tf-1.29.22.dist-info/WHEEL
onnx2tf-1.29.22.dist-info/entry_points.txt
onnx2tf-1.29.22.dist-info/METADATA
onnx2tf-1.29.22.dist-info/RECORD
