Metadata-Version: 2.4
Name: onnx2tf
Version: 1.29.22
Summary: Self-Created Tools to convert ONNX files (NCHW) to TensorFlow/TFLite/Keras format (NHWC). The purpose of this tool is to solve the massive Transpose extrapolation problem in onnx-tensorflow (onnx-tf).
Keywords: onnx,tensorflow,tflite,keras,deep-learning,machine-learning
Author: Katsuya Hyodo
Author-email: Katsuya Hyodo <rmsdh122@yahoo.co.jp>
License-Expression: MIT
Classifier: Development Status :: 5 - Production/Stable
Classifier: Intended Audience :: Developers
Classifier: Intended Audience :: Science/Research
Classifier: License :: OSI Approved :: MIT License
Classifier: Operating System :: POSIX :: Linux
Classifier: Operating System :: Unix
Classifier: Programming Language :: Python :: 3
Classifier: Programming Language :: Python :: 3.10
Classifier: Programming Language :: Python :: 3.11
Classifier: Topic :: Scientific/Engineering :: Artificial Intelligence
Requires-Dist: requests==2.32.5
Requires-Dist: numpy==1.26.4
Requires-Dist: onnx==1.19.1
Requires-Dist: onnxruntime==1.23.0
Requires-Dist: opencv-python==4.11.0.86
Requires-Dist: onnxsim==0.4.36
Requires-Dist: onnxoptimizer==0.4.2
Requires-Dist: ai-edge-litert==2.1.0
Requires-Dist: tensorflow==2.19.0
Requires-Dist: tf-keras==2.19.0
Requires-Dist: onnx-graphsurgeon==0.5.8
Requires-Dist: simple-onnx-processing-tools==1.1.32
Requires-Dist: psutil==5.9.5
Requires-Dist: protobuf==4.25.5
Requires-Dist: h5py==3.11.0
Requires-Dist: ml-dtypes==0.5.1
Requires-Dist: flatbuffers==25.12.19
Requires-Python: >=3.10.12
Project-URL: Homepage, https://github.com/PINTO0309/onnx2tf
Project-URL: Repository, https://github.com/PINTO0309/onnx2tf
Project-URL: Documentation, https://github.com/PINTO0309/onnx2tf#readme
Project-URL: Issues, https://github.com/PINTO0309/onnx2tf/issues
